TSDAL/__init__.py
TSDAL/funsplit.py
TSDAL/msal.py
TSDAL/patch.py
TSDAL-0.0.4.dist-info/LICENSE
TSDAL-0.0.4.dist-info/METADATA
TSDAL-0.0.4.dist-info/WHEEL
TSDAL-0.0.4.dist-info/top_level.txt
TSDAL-0.0.4.dist-info/RECORD
